panoramic/cli/__init__.py
panoramic/cli/__main__.py
panoramic/cli/__version__.py
panoramic/cli/analytics.py
panoramic/cli/cli.py
panoramic/cli/clients.py
panoramic/cli/command.py
panoramic/cli/connections.py
panoramic/cli/context.py
panoramic/cli/controller.py
panoramic/cli/dbt.py
panoramic/cli/diff.py
panoramic/cli/errors.py
panoramic/cli/executor.py
panoramic/cli/field_mapper.py
panoramic/cli/file_utils.py
panoramic/cli/identifier_generator.py
panoramic/cli/join_detector.py
panoramic/cli/logging.py
panoramic/cli/model_mapper.py
panoramic/cli/pano_model.py
panoramic/cli/paths.py
panoramic/cli/print.py
panoramic/cli/py.typed
panoramic/cli/refresh.py
panoramic/cli/scan.py
panoramic/cli/state.py
panoramic/cli/supported_version.py
panoramic/cli/validate.py
panoramic/cli/companies/__init__.py
panoramic/cli/companies/client.py
panoramic/cli/config/__init__.py
panoramic/cli/config/analytics.py
panoramic/cli/config/auth.py
panoramic/cli/config/companies.py
panoramic/cli/config/field.py
panoramic/cli/config/identifier.py
panoramic/cli/config/join.py
panoramic/cli/config/metadata.py
panoramic/cli/config/model.py
panoramic/cli/config/source.py
panoramic/cli/config/storage.py
panoramic/cli/config/transform.py
panoramic/cli/config/virtual_data_source.py
panoramic/cli/field/__init__.py
panoramic/cli/field/client.py
panoramic/cli/identifier/__init__.py
panoramic/cli/identifier/client.py
panoramic/cli/join/__init__.py
panoramic/cli/join/client.py
panoramic/cli/local/__init__.py
panoramic/cli/local/executor.py
panoramic/cli/local/get.py
panoramic/cli/local/reader.py
panoramic/cli/local/writer.py
panoramic/cli/metadata/__init__.py
panoramic/cli/metadata/client.py
panoramic/cli/model/__init__.py
panoramic/cli/model/client.py
panoramic/cli/physical_data_source/__init__.py
panoramic/cli/physical_data_source/client.py
panoramic/cli/remote/__init__.py
panoramic/cli/remote/executor.py
panoramic/cli/remote/get.py
panoramic/cli/remote/writer.py
panoramic/cli/schemas/__init__.py
panoramic_cli-1.7.1.dist-info/LICENSE
panoramic_cli-1.7.1.dist-info/METADATA
panoramic_cli-1.7.1.dist-info/WHEEL
panoramic_cli-1.7.1.dist-info/entry_points.txt
panoramic_cli-1.7.1.dist-info/top_level.txt
panoramic_cli-1.7.1.dist-info/RECORD
