Metadata-Version: 2.1
Name: panoramic-cli
Version: 1.7.1
Summary: Panoramic Command Line Tool
Home-page: https://github.com/panoramichq/panoramic-cli
Author: Panoramic
Maintainer: Panoramic
License: UNKNOWN
Project-URL: Source Code, https://github.com/panoramichq/panoramic-cli
Platform: UNKNOWN
Classifier: Development Status :: 5 - Production/Stable
Classifier: License :: OSI Approved
Classifier: License :: OSI Approved :: MIT License
Classifier: Programming Language :: Python :: 3
Classifier: Programming Language :: Python :: 3.6
Classifier: Programming Language :: Python :: 3.7
Classifier: Programming Language :: Python :: 3.8
Classifier: Programming Language :: Python :: 3.9
Requires-Python: >=3.6
Requires-Dist: panoramic-auth (>=0.2.0)
Requires-Dist: click (>=7.1.2)
Requires-Dist: colorama (>=0.4.3)
Requires-Dist: PyYAML (==5.3.1)
Requires-Dist: packaging (>=20.4)
Requires-Dist: tqdm (>=4.47.0.)
Requires-Dist: python-dotenv (>=0.14.0)
Requires-Dist: jsonschema (>=3.0)
Requires-Dist: requests (>=2.18.0)
Requires-Dist: dbt (>=0.18.1)
Requires-Dist: analytics-python (==1.2.9)
Requires-Dist: importlib-resources ; python_version < "3.7"
Provides-Extra: dev
Requires-Dist: pytest (>=5.3.5) ; extra == 'dev'
Requires-Dist: responses (>=0.10.14) ; extra == 'dev'
Requires-Dist: freezegun (>=0.3.15) ; extra == 'dev'
Requires-Dist: pytest-recording (>=0.8.1) ; extra == 'dev'
Requires-Dist: mypy (>=0.790) ; extra == 'dev'
Requires-Dist: flake8 (>=3.8.3) ; extra == 'dev'
Requires-Dist: black (==20.8b0) ; extra == 'dev'
Requires-Dist: pre-commit (>=2.1.1) ; extra == 'dev'
Provides-Extra: tests
Requires-Dist: pytest (>=5.3.5) ; extra == 'tests'
Requires-Dist: responses (>=0.10.14) ; extra == 'tests'
Requires-Dist: freezegun (>=0.3.15) ; extra == 'tests'
Requires-Dist: pytest-recording (>=0.8.1) ; extra == 'tests'
